django_user_guide-0.11.0.dist-info/DESCRIPTION.rst
django_user_guide-0.11.0.dist-info/METADATA
django_user_guide-0.11.0.dist-info/metadata.json
django_user_guide-0.11.0.dist-info/RECORD
django_user_guide-0.11.0.dist-info/top_level.txt
django_user_guide-0.11.0.dist-info/WHEEL
user_guide/__init__.py
user_guide/admin.py
user_guide/apps.py
user_guide/models.py
user_guide/urls.py
user_guide/version.py
user_guide/views.py
user_guide/migrations/0001_initial.py
user_guide/migrations/__init__.py
user_guide/static/user_guide/build/django-user-guide.css
user_guide/static/user_guide/build/django-user-guide.js
user_guide/templates/user_guide/window.html
user_guide/templatetags/__init__.py
user_guide/templatetags/user_guide_tags.py
user_guide/tests/__init__.py
user_guide/tests/admin_tests.py
user_guide/tests/model_tests.py
user_guide/tests/no_admin_tests.py
user_guide/tests/templatetag_tests.py
user_guide/tests/urls_tests.py
user_guide/tests/view_tests.py
