Metadata-Version: 2.0
Name: django-user-guide
Version: 0.11.0
Summary: Show configurable HTML guides to users.
Home-page: https://github.com/ambitioninc/django-user-guide
Author: Jeff McRiffey
Author-email: jeff.mcriffey@ambition.com
License: MIT
Platform: UNKNOWN
Classifier: Programming Language :: Python
Classifier: Programming Language :: Python :: 2.7
Classifier: Programming Language :: Python :: 3.4
Classifier: Programming Language :: Python :: 3.5
Classifier: Intended Audience :: Developers
Classifier: License :: OSI Approved :: MIT License
Classifier: Operating System :: OS Independent
Classifier: Framework :: Django
Classifier: Framework :: Django :: 1.8
Classifier: Framework :: Django :: 1.9
Requires-Dist: Django (>=1.8)
